hydrachain_explorer_requester/__init__.py
hydrachain_explorer_requester/explorer_requester.py
hydrachain_explorer_requester/explorer_url.py
hydrachain_explorer_requester/enum/__init__.py
hydrachain_explorer_requester/enum/address_balance_category.py
hydrachain_explorer_requester/query_parameters/__init__.py
hydrachain_explorer_requester/query_parameters/address_balance_history_query_parameters.py
hydrachain_explorer_requester/query_parameters/biggest_miners_query_parameters.py
hydrachain_explorer_requester/query_parameters/block_query_parameters.py
hydrachain_explorer_requester/query_parameters/blocks_query_parameters.py
hydrachain_explorer_requester/query_parameters/call_contract_query_parameters.py
hydrachain_explorer_requester/query_parameters/pagination_query_parameters.py
hydrachain_explorer_requester/query_parameters/query_parameter.py
hydrachain_explorer_requester/query_parameters/recent_blocks_query_parameters.py
hydrachain_explorer_requester/query_parameters/rich_list_query_parameters.py
hydrachain_explorer_requester/query_parameters/search_logs_query_parameters.py
hydrachain_explorer_requester/query_parameters/tokens_query_parameters.py
hydrachain_explorer_requester/query_parameters/transactions_query_parameters.py
hydrachain_explorer_requester-1.0.0.dist-info/METADATA
hydrachain_explorer_requester-1.0.0.dist-info/WHEEL
hydrachain_explorer_requester-1.0.0.dist-info/licenses/LICENSE
hydrachain_explorer_requester-1.0.0.dist-info/RECORD
