Metadata-Version: 2.1
Name: hydrachain-explorer-requester
Version: 1.0.0
Summary: A simple Python library for easily accessing the Hydrachain Explorer API
Project-URL: Source, https://github.com/ItsGosho/hydrachain-explorer-requester
Author: Georgi Peev
License-File: LICENSE
Keywords: hydra,hydrachain
Classifier: Intended Audience :: Developers
Classifier: License :: OSI Approved :: MIT License
Classifier: Operating System :: OS Independent
Classifier: Programming Language :: Python :: 3.11
Requires-Python: >=3.11
Requires-Dist: requests<3,>=2.28.1
